colourup/__init__.py
colourup/pinput.py
colourup/title.py
colourup/styles/__init__.py
colourup/styles/bg.py
colourup/styles/fg.py
colourup/styles/style.py
colourup-0.1.4.dist-info/LICENSE
colourup-0.1.4.dist-info/METADATA
colourup-0.1.4.dist-info/WHEEL
colourup-0.1.4.dist-info/top_level.txt
colourup-0.1.4.dist-info/RECORD
